[
null,
{"id":1,"animationId":41,"consumable":true,"damage":{"critical":false,"elementId":0,"formula":"0","type":0,"variance":20},"description":"HP回復　小","effects":[{"code":11,"dataId":0,"value1":0.25,"value2":0}],"hitType":0,"iconIndex":176,"itypeId":1,"name":"ポーション","note":"","occasion":0,"price":50,"repeats":1,"scope":7,"speed":0,"successRate":100,"tpGain":0},
{"id":2,"animationId":41,"consumable":true,"damage":{"critical":false,"elementId":0,"formula":"0","type":0,"variance":20},"description":"HP回復　中","effects":[{"code":11,"dataId":0,"value1":0.5,"value2":0}],"hitType":0,"iconIndex":176,"itypeId":1,"name":"ハイポーション","note":"","occasion":0,"price":500,"repeats":1,"scope":7,"speed":0,"successRate":100,"tpGain":0},
{"id":3,"animationId":41,"consumable":true,"damage":{"critical":false,"elementId":0,"formula":"0","type":0,"variance":20},"description":"HP回復　大","effects":[{"code":11,"dataId":0,"value1":1,"value2":0}],"hitType":0,"iconIndex":176,"itypeId":1,"name":"エクスポーション","note":"","occasion":0,"price":5000,"repeats":1,"scope":7,"speed":0,"successRate":100,"tpGain":0},
{"id":4,"animationId":42,"consumable":true,"damage":{"critical":false,"elementId":0,"formula":"0","type":0,"variance":20},"description":"MP回復　小","effects":[{"code":12,"dataId":0,"value1":0.25,"value2":0}],"hitType":0,"iconIndex":176,"itypeId":1,"name":"マインドアップ","note":"","occasion":0,"price":100,"repeats":1,"scope":7,"speed":0,"successRate":100,"tpGain":0},
{"id":5,"animationId":42,"consumable":true,"damage":{"critical":false,"elementId":0,"formula":"0","type":0,"variance":20},"description":"MP回復　中","effects":[{"code":12,"dataId":0,"value1":0.5,"value2":0}],"hitType":0,"iconIndex":176,"itypeId":1,"name":"マインドハイアップ","note":"","occasion":0,"price":1000,"repeats":1,"scope":7,"speed":0,"successRate":100,"tpGain":0},
{"id":6,"animationId":42,"consumable":true,"damage":{"critical":false,"elementId":0,"formula":"0","type":0,"variance":20},"description":"MP回復　大","effects":[{"code":12,"dataId":0,"value1":1,"value2":0}],"hitType":0,"iconIndex":176,"itypeId":1,"name":"マナプリズム","note":"","occasion":0,"price":10000,"repeats":1,"scope":7,"speed":0,"successRate":100,"tpGain":0},
{"id":7,"animationId":45,"consumable":true,"damage":{"critical":false,"elementId":0,"formula":"0","type":0,"variance":20},"description":"状態異常回復","effects":[{"code":22,"dataId":4,"value1":1,"value2":0},{"code":22,"dataId":5,"value1":1,"value2":0},{"code":22,"dataId":6,"value1":1,"value2":0},{"code":22,"dataId":7,"value1":1,"value2":0},{"code":22,"dataId":8,"value1":1,"value2":0},{"code":22,"dataId":9,"value1":1,"value2":0},{"code":22,"dataId":10,"value1":1,"value2":0},{"code":22,"dataId":11,"value1":1,"value2":0},{"code":22,"dataId":12,"value1":1,"value2":0},{"code":22,"dataId":13,"value1":1,"value2":0},{"code":22,"dataId":14,"value1":1,"value2":0},{"code":22,"dataId":15,"value1":1,"value2":0}],"hitType":0,"iconIndex":176,"itypeId":1,"name":"万能薬","note":"","occasion":0,"price":300,"repeats":1,"scope":7,"speed":0,"successRate":100,"tpGain":0},
{"id":8,"animationId":49,"consumable":true,"damage":{"critical":false,"elementId":0,"formula":"b.mhp","type":3,"variance":0},"description":"戦闘不能回復","effects":[{"code":22,"dataId":1,"value1":1,"value2":0}],"hitType":0,"iconIndex":176,"itypeId":1,"name":"生命の霊薬","note":"","occasion":0,"price":3000,"repeats":1,"scope":9,"speed":0,"successRate":100,"tpGain":0},
{"id":9,"animationId":46,"consumable":true,"damage":{"critical":false,"elementId":0,"formula":"0","type":0,"variance":20},"description":"TP増加　小","effects":[{"code":13,"dataId":0,"value1":20,"value2":0}],"hitType":0,"iconIndex":274,"itypeId":1,"name":"ブラウニー","note":"","occasion":0,"price":200,"repeats":1,"scope":7,"speed":0,"successRate":100,"tpGain":0},
{"id":10,"animationId":46,"consumable":true,"damage":{"critical":false,"elementId":0,"formula":"0","type":0,"variance":20},"description":"TP増加　中","effects":[{"code":13,"dataId":0,"value1":40,"value2":0}],"hitType":0,"iconIndex":274,"itypeId":1,"name":"クレープ・マリエット","note":"","occasion":0,"price":400,"repeats":1,"scope":7,"speed":0,"successRate":100,"tpGain":0},
{"id":11,"animationId":0,"consumable":true,"damage":{"critical":false,"elementId":0,"formula":"0","type":0,"variance":20},"description":"アイテムとして使用すると武器に変化する","effects":[{"code":44,"dataId":1,"value1":1,"value2":0}],"hitType":0,"iconIndex":97,"itypeId":1,"name":"最強の剣","note":"","occasion":0,"price":0,"repeats":1,"scope":11,"speed":0,"successRate":100,"tpGain":0}
]